tes_thermo/__init__.py
tes_thermo/eos/__init__.py
tes_thermo/eos/eos.py
tes_thermo/gibbs/__init__.py
tes_thermo/gibbs/gibbs.py
tes_thermo/solver/README.txt
tes_thermo/solver/__init__.py
tes_thermo/solver/bin/coinmumps-3.dll
tes_thermo/solver/bin/ipopt-3.dll
tes_thermo/solver/bin/ipopt.exe
tes_thermo/solver/bin/ipopt_sens.exe
tes_thermo/solver/bin/ipoptamplinterface-3.dll
tes_thermo/solver/bin/libifcoremd.dll
tes_thermo/solver/bin/libiomp5md.dll
tes_thermo/solver/bin/libmmd.dll
tes_thermo/solver/bin/sipopt-3.dll
tes_thermo/solver/bin/svml_dispmd.dll
tes_thermo/solver/include/coin-or/AmplTNLP.hpp
tes_thermo/solver/include/coin-or/IpAlgBuilder.hpp
tes_thermo/solver/include/coin-or/IpAlgStrategy.hpp
tes_thermo/solver/include/coin-or/IpAlgTypes.hpp
tes_thermo/solver/include/coin-or/IpAugSystemSolver.hpp
tes_thermo/solver/include/coin-or/IpBlas.hpp
tes_thermo/solver/include/coin-or/IpCachedResults.hpp
tes_thermo/solver/include/coin-or/IpCompoundMatrix.hpp
tes_thermo/solver/include/coin-or/IpCompoundSymMatrix.hpp
tes_thermo/solver/include/coin-or/IpCompoundVector.hpp
tes_thermo/solver/include/coin-or/IpConvCheck.hpp
tes_thermo/solver/include/coin-or/IpDebug.hpp
tes_thermo/solver/include/coin-or/IpDenseVector.hpp
tes_thermo/solver/include/coin-or/IpDiagMatrix.hpp
tes_thermo/solver/include/coin-or/IpEqMultCalculator.hpp
tes_thermo/solver/include/coin-or/IpException.hpp
tes_thermo/solver/include/coin-or/IpExpansionMatrix.hpp
tes_thermo/solver/include/coin-or/IpGenTMatrix.hpp
tes_thermo/solver/include/coin-or/IpHessianUpdater.hpp
tes_thermo/solver/include/coin-or/IpIdentityMatrix.hpp
tes_thermo/solver/include/coin-or/IpIpoptAlg.hpp
tes_thermo/solver/include/coin-or/IpIpoptApplication.hpp
tes_thermo/solver/include/coin-or/IpIpoptCalculatedQuantities.hpp
tes_thermo/solver/include/coin-or/IpIpoptData.hpp
tes_thermo/solver/include/coin-or/IpIpoptNLP.hpp
tes_thermo/solver/include/coin-or/IpIterateInitializer.hpp
tes_thermo/solver/include/coin-or/IpIteratesVector.hpp
tes_thermo-0.1.0.dist-info/licenses/LICENCE
tes_thermo-0.1.0.dist-info/METADATA
tes_thermo-0.1.0.dist-info/WHEEL
tes_thermo-0.1.0.dist-info/top_level.txt
tes_thermo-0.1.0.dist-info/RECORD
