Metadata-Version: 2.4
Name: tes_thermo
Version: 0.1.0
Summary: TeS is a tool for simulating reaction processes. It uses the Gibbs energy minimization approach with the help of Pyomo and Ipopt as solvers.
Author: Julles Mitoura, Antonio Freitas and Adriano Mariano
Author-email: mitoura96@outlook.com
License: MIT License
Keywords: gibbs,thermodynamics,virial,reactions,simulation,pyomo
License-File: LICENCE
Requires-Dist: pandas==2.3.1
Requires-Dist: numpy==2.3.1
Requires-Dist: scipy==1.16.0
Requires-Dist: pyomo==6.9.2
Dynamic: author
Dynamic: author-email
Dynamic: description
Dynamic: description-content-type
Dynamic: keywords
Dynamic: license
Dynamic: license-file
Dynamic: requires-dist
Dynamic: summary
